Workbook

Sheet OnBase Coding
B2: Cost Category | C2: Description | D2: Unit # | E2: Nature #
B3: Daikin ONE | C3: Total Cloud costs for Wi-Fi Connected Thermostats (Sustaining) | D3: 1900220 | E3: 76410
B4: Cloud Services | C4: COGS for Cloud Services / SkyportCare | D4: 1980230 | E4: 50075
D12: 220
C13: 3
J14: 7

Sheet FY25 Total
C1: ='FY25'!B1 -> 447756
C3: April | D3: May | E3: June | F3: July | G3: August | H3: September | I3: October | J3: November | K3: December | L3: January | M3: February | N3: March | O3: FY25 Total
B4: Monthly Smart Thermostat Sales (All Stats & Brands) | C4: 15439 | D4: 18909 | E4: 21066 | F4: 20739 | G4: 15453 | H4: 12025 | I4: 12748 | J4: 9150 | O4: =SUM(C4:N4) -> 125529
B5: Total Daikin One Sales (All-time) | C5: =C4+C1 -> 463195 | D5: =C5+D4 -> 482104 | E5: =D5+E4 -> 503170 | F5: =E5+F4 -> 523909 | G5: =F5+G4 -> 539362 | H5: =G5+H4 -> 551387 | I5: =H5+I4 -> 564135 | J5: =I5+J4 -> 573285 | K5: =J5+K4 -> 573285 | ... N5: =M5+N4 -> 573285
B6: Total D/A/G Thermostats Connected to Wi-Fi | C6: 269593 | D6: 294481 | E6: 299991 | F6: 304528 | G6: 294532 | H6: 302743 | I6: 311895 | J6: 318949
B7: AWS Cost (DNA) | C7: 35381.18 | D7: 39890.72 | E7: 38431.53 | F7: 38723.87 | G7: 40085.3 | H7: 38310.35 | I7: =36571.46+150.31 -> 36721.77 | J7: ='FY25'!I7 -> 42241.7 | K7: ='FY25'!J7 -> 17017.5 | L7: ='FY25'!K7 -> 55217.23 | O7: =SUM(C7:N7) -> 382021.15
B8: AWS Cost (Venstar) | C8: 95495.13 | D8: 90495.13 | E8: 94021.9 | F8: 105960.37 | G8: 122230.54 | H8: 121662.25 | I8: 117958.94 | J8: 126325.85 | K8: 121706.71 | L8: 133108.79 | O8: =SUM(C8:N8) -> 1128965.6
B9: AWS Cost (Total) | C9: =SUM(C7:C8) -> 130876.31 | D9: =SUM(D7:D8) -> 130385.85 | E9: =SUM(E7:E8) -> 132453.43 | F9: =SUM(F7:F8) -> 144684.24 | G9: =SUM(G7:G8) -> 162315.84 | H9: =SUM(H7:H8) -> 159972.6 | I9: =SUM(I7:I8) -> 154680.71 | J9: =SUM(J7:J8) -> 168567.55 | ... O9: =SUM(O7:O8) -> 1510986.8
B10: Cost per D1+ Connection (DNA) | C10: =C7/C6 -> 0.13123924 | D10: =D7/D6 -> 0.1354611 | E10: =E7/E6 -> 0.12810894 | F10: =F7/F6 -> 0.12716029 | G10: =G7/G6 -> 0.13609828 | H10: =H7/H6 -> 0.12654413 | I10: =I7/I6 -> 0.1177376 | J10: =J7/J6 -> 0.1324403 | ... N10: =N7/N6 -> #DIV/0!
B11: Cost per D1+ Connection (Venstar) | C11: =C8/C6 -> 0.35421962 | D11: =D8/D6 -> 0.3073038 | E11: =E8/E6 -> 0.31341574 | F11: =F8/F6 -> 0.34794952 | G11: =G8/G6 -> 0.41499919 | H11: =H8/H6 -> 0.40186643 | I11: =I8/I6 -> 0.3782008 | J11: =J8/J6 -> 0.39606912 | ... N11: =N8/N6 -> #DIV/0!
B12: Cost per D1+ Connection (Total) | C12: =C11+C10 -> 0.48545886 | D12: =D11+D10 -> 0.4427649 | E12: =E11+E10 -> 0.44152468 | F12: =F11+F10 -> 0.47510981 | G12: =G11+G10 -> 0.55109747 | H12: =H11+H10 -> 0.52841057 | I12: =I11+I10 -> 0.49593841 | J12: =J11+J10 -> 0.52850942 | ... N12: =N11+N10 -> #DIV/0!
B13: Percentage of all D1+ Connected to Wi-Fi | C13: =C6/C5 -> 0.58202917 | D13: =D6/D5 -> 0.61082464 | E13: =E6/E5 -> 0.59620208 | F13: =F6/F5 -> 0.58126125 | G13: =G6/G5 -> 0.54607481 | H13: =H6/H5 -> 0.5490572 | I13: =I6/I5 -> 0.55287298 | J13: =J6/J5 -> 0.5563533 | ... N13: =N6/N5 -> 0
B15: Vs Prior Month (%) | C15: 1 | D15: =D9/C9 -> 0.99625249 | E15: =E9/D9 -> 1.0158574 | F15: =F9/E9 -> 1.0923405 | G15: =G9/F9 -> 1.1218626 | H15: =H9/G9 -> 0.9855637 | I15: =I9/H9 -> 0.96692002 | J15: =J9/I9 -> 1.0897775 | K15: =K9/J9 -> 0.82295916 | L15: =L9/K9 -> 1.357557
B16: Vs April % | C16: 1 | D16: =D9/$C$9 -> 0.99625249 | E16: =E9/$C$9 -> 1.0120505 | F16: =F9/$C$9 -> 1.1055037 | G16: =G9/$C$9 -> 1.2402232 | H16: =H9/$C$9 -> 1.222319 | I16: =I9/$C$9 -> 1.1818847 | J16: =J9/$C$9 -> 1.2879913 | K16: =K9/$C$9 -> 1.0599643 | L16: =L9/$C$9 -> 1.4389619

Sheet FY25_PB
A1: Prior Years (FY19-FY22) Daikin One+ Sales | B1: ='FY24'!M5 -> 447756
B3: April | C3: May | D3: June | E3: July | F3: August | G3: September | H3: October | I3: November | J3: December | K3: January | L3: February | M3: March | N3: FY25 Total
A4: Monthly Smart Thermostat Sales (All Stats & Brands) | B4: 15439 | C4: 18909 | D4: 21066 | E4: 20739 | F4: 15453 | G4: 12025 | H4: 12748 | I4: 9042 | J4: 13399 | K4: 11424 | L4: 12064 | N4: =SUM(B4:M4) -> 162308
A5: Total Daikin One Sales (All-time) | B5: =B4+B1 -> 463195 | C5: =B5+C4 -> 482104 | D5: =C5+D4 -> 503170 | E5: =D5+E4 -> 523909 | F5: =E5+F4 -> 539362 | G5: =F5+G4 -> 551387 | H5: =G5+H4 -> 564135 | I5: =H5+I4 -> 573177 | J5: =I5+J4 -> 586576 | ... M5: =L5+M4 -> 610064
A6: Total D/A/G Thermostats Connected to Wi-Fi | B6: 269593 | C6: 294481 | D6: 299991 | E6: 304528 | F6: 294532 | G6: 302743 | H6: 311895 | I6: 318949 | J6: 328155 | K6: 335302 | L6: 341229
B7: =-'FY24'!M6+FY25_PB!B6 -> 22797 | C7: =C6-B6 -> 24888 | D7: =D6-C6 -> 5510 | E7: =E6-D6 -> 4537 | F7: =F6-E6 -> -9996 | G7: =G6-F6 -> 8211 | H7: =H6-G6 -> 9152 | I7: =I6-H6 -> 7054 | J7: =J6-I6 -> 9206 | ... L7: =L6-K6 -> 5927
A8: AWS Cost | B8: 35381.18 | C8: 39890.72 | D8: 38431.53 | E8: 38723.87 | F8: 40085.3 | G8: 38310.35 | H8: =36571.46+150.31 -> 36721.77 | I8: =35017.42+7224.28 -> 42241.7 | J8: =6225.32+10792.18 -> 17017.5 | K8: =45677.6+9539.63 -> 55217.23 | L8: =1231.23+33781.29 -> 35012.52 | N8: =SUM(B8:M8) -> 417033.67
A9: Cost per D1+ Connection (Per month) | B9: =B8/B6 -> 0.13123924 | C9: =C8/C6 -> 0.1354611 | D9: =D8/D6 -> 0.12810894 | E9: =E8/E6 -> 0.12716029 | F9: =F8/F6 -> 0.13609828 | G9: =G8/G6 -> 0.12654413 | H9: =H8/H6 -> 0.1177376 | I9: =I8/I6 -> 0.1324403 | ... M9: =M8/M6 -> #DIV/0! | N9: =N8/M6 -> #DIV/0!
A10: Percentage of all D1+ Connected to Wi-Fi | B10: =B6/B5 -> 0.58202917 | C10: =C6/C5 -> 0.61082464 | D10: =D6/D5 -> 0.59620208 | E10: =E6/E5 -> 0.58126125 | F10: =F6/F5 -> 0.54607481 | G10: =G6/G5 -> 0.5490572 | H10: =H6/H5 -> 0.55287298 | I10: =I6/I5 -> 0.55645813 | ... M10: =M6/M5 -> 0
A11: New Cloud Services Sales & Activations (Monthly) | B11: 680 | C11: 730 | D11: 827 | E11: 954 | F11: 856 | G11: 707 | H11: 847 | I11: 873 | J11: 977 | K11: 962 | L11: 1014 | N11: =SUM(B11:M11) -> 9427
A12: Active Cloud Services Plans (EOM) | B12: 10265 | C12: 10400 | D12: 10584 | E12: 10720 | F12: 10917 | G12: 11076 | H12: 11280 | I12: 11521 | J12: 11833 | K12: 11963 | L12: 12165
A13: Daikin One Cloud Services COGS | B13: =B9*B12 -> 1347.1708 | C13: =C9*C12 -> 1408.7954 | D13: =D9*D12 -> 1355.9051 | E13: =E9*E12 -> 1363.1584 | F13: =F9*F12 -> 1485.785 | G13: =G9*G12 -> 1401.6028 | H13: =H9*H12 -> 1328.0802 | I13: =I9*I12 -> 1525.8447 | ... M13: =M9*M12 -> #DIV/0! | N13: =SUM(B13:M13) -> #DIV/0!
A15: Daikin One Cost | B15: =B8-B13 -> 34034.009 | C15: =C8-C13 -> 38481.925 | D15: =D8-D13 -> 37075.625 | E15: =E8-E13 -> 37360.712 | F15: =F8-F13 -> 38599.515 | G15: =G8-G13 -> 36908.747 | H15: =H8-H13 -> 35393.69 | I15: =I8-I13 -> 40715.855 | ... M15: =M8-M13 -> #DIV/0!
A17: Tax | B17: 2190.65 | C17: 2469.92 | D17: 2376.89 | E17: 2397.63 | F17: 2481.93 | G17: 2372.05 | H17: =2264.36+9.31 -> 2273.67 | I17: =2168.16+447.28 -> 2615.44 | J17: =668.18+387.3 -> 1055.48 | K17: =2832.08+590.63 -> 3422.71 | L17: =76.23+2095.42 -> 2171.65
A18: AWS Cost Less Tax | B18: =B8-B17 -> 33190.53 | C18: =C8-C17 -> 37420.8 | D18: =D8-D17 -> 36054.64 | E18: =E8-E17 -> 36326.24 | F18: =F8-F17 -> 37603.37 | G18: =G8-G17 -> 35938.3 | H18: =H8-H17 -> 34448.1 | I18: =I8-I17 -> 39626.26 | ... M18: =M8-M17 -> 0
A19: D1 Cost w/o tax & DOCS | B19: =B18-B13 -> 31843.359 | C19: =C18-C13 -> 36012.005 | D19: =D18-D13 -> 34698.735 | E19: =E18-E13 -> 34963.082 | F19: =F18-F13 -> 36117.585 | G19: =G18-G13 -> 34536.697 | H19: =H18-H13 -> 33120.02 | I19: =I18-I13 -> 38100.415 | ... M19: =M18-M13 -> #DIV/0!
B24: =L6-B6 -> 71636
B25: 246796

Sheet FY25
A1: Prior Years (FY19-FY22) Daikin One+ Sales | B1: ='FY24'!M5 -> 447756
B3: April | C3: May | D3: June | E3: July | F3: August | G3: September | H3: October | I3: November | J3: December | K3: January | L3: February | M3: March | N3: FY25 Total
A4: Monthly Smart Thermostat Sales (All Stats & Brands) | B4: 15439 | C4: 18909 | D4: 21066 | E4: 20739 | F4: 15453 | G4: 12025 | H4: 12748 | I4: 9042 | J4: 13399 | K4: 11424 | L4: 12064 | M4: 19158 | N4: =SUM(B4:M4) -> 181466
A5: Total Daikin One Sales (All-time) | B5: =B4+B1 -> 463195 | C5: =B5+C4 -> 482104 | D5: =C5+D4 -> 503170 | E5: =D5+E4 -> 523909 | F5: =E5+F4 -> 539362 | G5: =F5+G4 -> 551387 | H5: =G5+H4 -> 564135 | I5: =H5+I4 -> 573177 | J5: =I5+J4 -> 586576 | ... M5: =L5+M4 -> 629222
A6: Total D/A/G Thermostats Connected to Wi-Fi | B6: 269593 | C6: 294481 | D6: 299991 | E6: 304528 | F6: 294532 | G6: 302743 | H6: 311895 | I6: 318949 | J6: 328155 | K6: 335302 | L6: 341229 | M6: 349395
A7: AWS Cost | B7: 35381.18 | C7: 39890.72 | D7: 38431.53 | E7: 38723.87 | F7: 40085.3 | G7: 38310.35 | H7: =36571.46+150.31 -> 36721.77 | I7: =35017.42+7224.28 -> 42241.7 | J7: =6225.32+10792.18 -> 17017.5 | K7: =45677.6+9539.63 -> 55217.23 | L7: =1231.23+33781.29 -> 35012.52 | M7: 45550.48 | N7: =SUM(B7:M7) -> 462584.15
A8: Cost per D1+ Connection (Per month) | B8: =B7/B6 -> 0.13123924 | C8: =C7/C6 -> 0.1354611 | D8: =D7/D6 -> 0.12810894 | E8: =E7/E6 -> 0.12716029 | F8: =F7/F6 -> 0.13609828 | G8: =G7/G6 -> 0.12654413 | H8: =H7/H6 -> 0.1177376 | I8: =I7/I6 -> 0.1324403 | ... M8: =M7/M6 -> 0.13036958 | N8: =N7/M6 -> 1.3239576
A9: Percentage of all D1+ Connected to Wi-Fi | B9: =B6/B5 -> 0.58202917 | C9: =C6/C5 -> 0.61082464 | D9: =D6/D5 -> 0.59620208 | E9: =E6/E5 -> 0.58126125 | F9: =F6/F5 -> 0.54607481 | G9: =G6/G5 -> 0.5490572 | H9: =H6/H5 -> 0.55287298 | I9: =I6/I5 -> 0.55645813 | ... M9: =M6/M5 -> 0.55528097
A10: New Cloud Services Sales & Activations (Monthly) | B10: 680 | C10: 730 | D10: 827 | E10: 954 | F10: 856 | G10: 707 | H10: 847 | I10: 873 | J10: 977 | K10: 962 | L10: 1014 | M10: 921 | N10: =SUM(B10:M10) -> 10348
A11: Active Cloud Services Plans (EOM) | B11: 10265 | C11: 10400 | D11: 10584 | E11: 10720 | F11: 10917 | G11: 11076 | H11: 11280 | I11: 11521 | J11: 11833 | K11: 11963 | L11: 12165 | M11: 12459
A12: Daikin One Cloud Services COGS | B12: =B8*B11 -> 1347.1708 | C12: =C8*C11 -> 1408.7954 | D12: =D8*D11 -> 1355.9051 | E12: =E8*E11 -> 1363.1584 | F12: =F8*F11 -> 1485.785 | G12: =G8*G11 -> 1401.6028 | H12: =H8*H11 -> 1328.0802 | I12: =I8*I11 -> 1525.8447 | ... M12: =M8*M11 -> 1624.2746 | N12: =SUM(B12:M12) -> 16672.525
A14: Daikin One Cost | B14: =B7-B12 -> 34034.009 | C14: =C7-C12 -> 38481.925 | D14: =D7-D12 -> 37075.625 | E14: =E7-E12 -> 37360.712 | F14: =F7-F12 -> 38599.515 | G14: =G7-G12 -> 36908.747 | H14: =H7-H12 -> 35393.69 | I14: =I7-I12 -> 40715.855 | ... M14: =M7-M12 -> 43926.205
A16: Tax | B16: 2190.65 | C16: 2469.92 | D16: 2376.89 | E16: 2397.63 | F16: 2481.93 | G16: 2372.05 | H16: =2264.36+9.31 -> 2273.67 | I16: =2168.16+447.28 -> 2615.44 | J16: =668.18+387.3 -> 1055.48 | K16: =2832.08+590.63 -> 3422.71 | L16: =76.23+2095.42 -> 2171.65
A17: AWS Cost Less Tax | B17: =B7-B16 -> 33190.53 | C17: =C7-C16 -> 37420.8 | D17: =D7-D16 -> 36054.64 | E17: =E7-E16 -> 36326.24 | F17: =F7-F16 -> 37603.37 | G17: =G7-G16 -> 35938.3 | H17: =H7-H16 -> 34448.1 | I17: =I7-I16 -> 39626.26 | ... M17: =M7-M16 -> 45550.48
A18: D1 Cost w/o tax & DOCS | B18: =B17-B12 -> 31843.359 | C18: =C17-C12 -> 36012.005 | D18: =D17-D12 -> 34698.735 | E18: =E17-E12 -> 34963.082 | F18: =F17-F12 -> 36117.585 | G18: =G17-G12 -> 34536.697 | H18: =H17-H12 -> 33120.02 | I18: =I17-I12 -> 38100.415 | ... M18: =M17-M12 -> 43926.205

Sheet FY24
A1: Prior Years (FY19-FY22) Daikin One+ Sales | B1: ='FY23'!M6 -> 288980
B3: April | C3: May | D3: June | E3: July | F3: August | G3: September | H3: October | I3: November | J3: December | K3: January | L3: February | M3: March | N3: FY24 Total
A4: Monthly Smart Thermostat Sales (All Stats & Brands) | B4: 11059 | C4: 14484 | D4: 20172 | E4: 21250 | F4: 18543 | G4: 12503 | H4: 12109 | I4: 8560 | J4: 9539 | K4: 7658 | L4: 10185 | M4: 12714 | N4: =SUM(B4:M4) -> 158776
A5: Total Daikin One Sales (All-time) | B5: =B4+B1 -> 300039 | C5: =B5+C4 -> 314523 | D5: =C5+D4 -> 334695 | E5: =D5+E4 -> 355945 | F5: =E5+F4 -> 374488 | G5: =F5+G4 -> 386991 | H5: =G5+H4 -> 399100 | I5: =H5+I4 -> 407660 | J5: =I5+J4 -> 417199 | ... M5: =L5+M4 -> 447756
A6: Total D/A/G Thermostats Connected to Wi-Fi | B6: 156063 | C6: 166317 | D6: 172806 | E6: 184126 | F6: 193334 | G6: 201802 | H6: 205000 | I6: 207754 | J6: 216362 | K6: 223917 | L6: 229685 | M6: 246796
A7: AWS Cost | B7: 47433.74 | C7: 37064.8 | D7: 82792.92 | E7: 57395.01 | F7: 50593.76 | G7: 37218.78 | H7: 35622.87 | I7: 30300.5 | J7: 31771.56 | K7: 32731.2 | L7: 22717.51 | M7: 33627.65 | N7: =SUM(B7:M7) -> 499270.3
A8: Cost per D1+ Connection (Per month) | B8: =B7/B6 -> 0.30393969 | C8: =C7/C6 -> 0.22285635 | D8: =D7/D6 -> 0.47910906 | E8: =E7/E6 -> 0.31171594 | F8: =F7/F6 -> 0.26169096 | G8: =G7/G6 -> 0.18443217 | H8: =H7/H6 -> 0.1737701 | I8: =I7/I6 -> 0.14584797 | ... M8: =M7/M6 -> 0.13625687 | N8: =N7/M6 -> 2.0230081
A9: Percentage of all D1+ Connected to Wi-Fi | B9: =B6/B5 -> 0.52014238 | C9: =C6/C5 -> 0.52879122 | D9: =D6/D5 -> 0.51630888 | E9: =E6/E5 -> 0.51728778 | F9: =F6/F5 -> 0.5162622 | G9: =G6/G5 -> 0.52146432 | H9: =H6/H5 -> 0.51365573 | I9: =I6/I5 -> 0.50962567 | ... M9: =M6/M5 -> 0.55118413
A10: New Cloud Services Sales & Activations (Monthly) | B10: 367 | C10: 613 | D10: 645 | E10: 859 | F10: 726 | G10: 546 | H10: 702 | I10: 668 | J10: 661 | K10: 765 | L10: 699 | M10: 600 | N10: =SUM(B10:M10) -> 7851
A11: Active Cloud Services Plans (EOM) | B11: 8177 | C11: =B11+C10 -> 8790 | D11: =C11+D10 -> 9435 | E11: 8628 | F11: 8879 | G11: 9434 | H11: 9690 | I11: 10236 | J11: 10826 | K11: 9612 | L11: 9874 | M11: 10062
A12: Daikin One Cloud Services COGS | B12: =B8*B11 -> 2485.3149 | C12: =C8*C11 -> 1958.9073 | D12: =D8*D11 -> 4520.394 | E12: =E8*E11 -> 2689.4852 | F12: =F8*F11 -> 2323.554 | G12: =G8*G11 -> 1739.9331 | H12: =H8*H11 -> 1683.8322 | I12: =I8*I11 -> 1492.8999 | ... M12: =M8*M11 -> 1371.0166 | N12: =SUM(B12:M12) -> 24236.725
A14: Daikin One Cost | B14: =B7-B12 -> 44948.425 | C14: =C7-C12 -> 35105.893 | D14: =D7-D12 -> 78272.526 | E14: =E7-E12 -> 54705.525 | F14: =F7-F12 -> 48270.206 | G14: =G7-G12 -> 35478.847 | H14: =H7-H12 -> 33939.038 | I14: =I7-I12 -> 28807.6 | ... M14: =M7-M12 -> 32256.633
A16: Tax | B16: 2936.94 | C16: 2294.96 | D16: 5126.14 | E16: 3551.02 | F16: 3132.56 | G16: 2304.48 | H16: 2205.67 | I16: 206.68 | J16: 1967.22 | K16: 2026.61 | L16: 1405.84 | M16: 2082.16
A17: AWS Cost Less Tax | B17: =B7-B16 -> 44496.8 | C17: =C7-C16 -> 34769.84 | D17: =D7-D16 -> 77666.78 | E17: =E7-E16 -> 53843.99 | F17: =F7-F16 -> 47461.2 | G17: =G7-G16 -> 34914.3 | H17: =H7-H16 -> 33417.2 | I17: =I7-I16 -> 30093.82 | ... M17: =M7-M16 -> 31545.49
A18: D1 Cost w/o tax & DOCS | B18: =B17-B12 -> 42011.485 | C18: =C17-C12 -> 32810.933 | D18: =D17-D12 -> 73146.386 | E18: =E17-E12 -> 51154.505 | F18: =F17-F12 -> 45137.646 | G18: =G17-G12 -> 33174.367 | H18: =H17-H12 -> 31733.368 | I18: =I17-I12 -> 28600.92 | ... M18: =M17-M12 -> 30174.473
A20: AWS Cost less tax & Credits | I20: =3336.14-206.68 -> 3129.46
A21: Daikin One allocation (AWS Cost - DOCS COGS) | I21: =I20-I12 -> 1636.5601

Sheet FY23
A1: Prior Years (FY19-FY22) Daikin One+ Sales | B1: ='FY22'!M5 -> 182477
A2: PY Active DOCS Licenses | B2: ='FY22'!M11 -> 1941
B4: April | C4: May | D4: June | E4: July | F4: August | G4: September | H4: October | I4: November | J4: December | K4: January | L4: February | M4: March
A5: Monthly Daikin Smart Thermostat Sales (All Stats & Brands) | B5: 7503 | C5: 9925 | D5: 13262 | E5: 10573 | F5: 11104 | G5: 7565 | H5: 7511 | I5: 6766 | J5: 6337 | K5: 7017 | L5: 7717 | M5: 11223
A6: Total Daikin One Sales (All-time) | B6: =B5+B1 -> 189980 | C6: =B6+C5 -> 199905 | D6: =C6+D5 -> 213167 | E6: =D6+E5 -> 223740 | F6: =E6+F5 -> 234844 | G6: =F6+G5 -> 242409 | H6: =G6+H5 -> 249920 | I6: =H6+I5 -> 256686 | J6: =I6+J5 -> 263023 | ... M6: =L6+M5 -> 288980
A7: Total D/A/G Thermostats Connected to Wi-Fi | B7: 99826 | C7: 105125 | D7: 114981 | E7: 121036 | F7: 127251 | G7: 132549 | H7: 131437 | I7: 135558 | J7: 139286 | K7: 142533 | L7: 146026 | M7: 149689
A8: AWS Cost | B8: 15760.3 | C8: 15257.3 | D8: 21779.63 | E8: 19202.23 | F8: 29564.35 | G8: 33665.58 | H8: 31284.8 | I8: 33313.44 | J8: 34260.46 | K8: 29606.56 | L8: 31647.81 | M8: 35050.03
A9: AWS Redshift (Pre-paid, 36 months July '21 - June '24) | B9: 633.86 | C9: 633.86 | D9: 633.86 | E9: 633.86 | F9: 633.86 | G9: 633.86 | H9: 633.86 | I9: 633.86 | J9: 0 | K9: 0 | L9: 0 | M9: 0
A10: Cost per D1+ Connection (Per month) | B10: =(B8+B9)/B7 -> 0.16422736 | C10: =(C8+C9)/C7 -> 0.15116442 | D10: =(D8+D9)/D7 -> 0.19493212 | E10: =(E8+E9)/E7 -> 0.16388587 | F10: =(F8+F9)/F7 -> 0.23731216 | G10: =(G8+G9)/G7 -> 0.258768 | H10: =(H8+H9)/H7 -> 0.2428438 | I10: =(I8+I9)/I7 -> 0.25042639 | ... M10: =(M8+M9)/M7 -> 0.23415234
A11: Percentage of all D1+ Connected to Wi-Fi | B11: =B7/B6 -> 0.52545531 | C11: =C7/C6 -> 0.52587479 | D11: =D7/D6 -> 0.539394 | E11: =E7/E6 -> 0.54096719 | F11: =F7/F6 -> 0.54185332 | G11: =G7/G6 -> 0.546799 | H11: =H7/H6 -> 0.52591629 | I11: =I7/I6 -> 0.52810827 | ... M11: =M7/M6 -> 0.51799086
A12: New Cloud Services Sales & Activations (Monthly) | B12: 367 | C12: 355 | D12: 652 | E12: 674 | F12: 636 | G12: 432 | H12: 502 | I12: 438 | J12: 368 | K12: 558 | L12: 435 | M12: 439
A13: Active Cloud Services Plans (EOM) | B13: 3639 | C13: 4025 | D13: 4651 | E13: =D13+E12 -> 5325 | F13: =E13+F12 -> 5961 | G13: =F13+G12 -> 6393 | H13: =G13+H12 -> 6895 | I13: =H13+I12 -> 7333 | J13: =I13+J12 -> 7701 | K13: =J13+K12 -> 8259 | L13: =K13+L12 -> 8694 | M13: =L13+M12 -> 9133
A14: Daikin One Cloud Services COGS | B14: =B10*B13 -> 597.62335 | C14: =C10*C13 -> 608.4368 | D14: =D10*D13 -> 906.62929 | E14: =E10*E13 -> 872.69225 | F14: =F10*F13 -> 1414.6178 | G14: =G10*G13 -> 1654.3038 | H14: =H10*H13 -> 1674.408 | I14: =I10*I13 -> 1836.3767 | ... M14: =M10*M13 -> 2138.5133
A16: Daikin One Cost | I16: =33313.44 - I14 -> 31477.063 | J16: =J8-J14 -> 32366.229 | K16: =K8-K14 -> 27891.023 | L16: =L8-L14 -> 29763.583 | M16: =M8-M14 -> 32911.517
L18: =L16-1958.75 -> 27804.833
A21: Total AWS Cost | B21: =B8+B9 -> 16394.16 | C21: =C8+C9 -> 15891.16 | D21: =D8+D9 -> 22413.49 | E21: =E8+E9 -> 19836.09 | F21: =F8+F9 -> 30198.21 | G21: =G8+G9 -> 34299.44 | H21: =H8+H9 -> 31918.66 | I21: =I8+I9 -> 33947.3 | ... M21: =M8+M9 -> 35050.03

Sheet FY22
A1: Prior Years (FY19-FY21) Daikin One+ Sales | B1: 104017
B3: April | C3: May | D3: June | E3: July | F3: August | G3: September | H3: October | I3: November | J3: December | K3: January | L3: February | M3: March
A4: Monthly Daikin One Smart Thermostat Sales | B4: 6501 | C4: 7196 | D4: 6983 | E4: 5111 | F4: 4105 | G4: 8035 | H4: 4553 | I4: 4923 | J4: 5963 | K4: 7581 | L4: 3972 | M4: 13537
A5: Total Daikin One Sales (All-time) | B5: =B4+B1 -> 110518 | C5: =B5+C4 -> 117714 | D5: =C5+D4 -> 124697 | E5: =D5+E4 -> 129808 | F5: =E5+F4 -> 133913 | G5: =F5+G4 -> 141948 | H5: =G5+H4 -> 146501 | I5: =H5+I4 -> 151424 | J5: =I5+J4 -> 157387 | ... M5: =L5+M4 -> 182477
A6: D1+ Connected to Wi-Fi | B6: 57638 | C6: 61619 | D6: 66518 | E6: 70208 | F6: 74951 | G6: 77997 | H6: 80779 | I6: 83789 | J6: 86251 | K6: 88317 | L6: 90841 | M6: 94908
A7: AWS Cost | B7: 7860.19 | C7: 7111.24 | D7: 6833.96 | E7: 7171.4 | F7: 8096.27 | G7: 10095.46 | H7: 10298.63 | I7: 11798.98 | J7: 11690.17 | K7: 15569.48 | L7: 16720.54 | M7: 15671.14
A8: AWS Redshift (Pre-paid, 36 months July '21 - June '24) | B8: 633.86 | C8: 633.86 | D8: 633.86 | E8: 633.86 | F8: 633.86 | G8: 633.86 | H8: 633.86 | I8: 633.86 | J8: 633.86 | K8: 633.86 | L8: 633.86 | M8: 633.86
A9: Cost per D1+ Connection | B9: =(B7+B8)/B6 -> 0.14736892 | C9: =(C7+C8)/C6 -> 0.12569337 | D9: =(D7+D8)/D6 -> 0.11226766 | E9: =(E7+E8)/E6 -> 0.11117337 | F9: =(F7+F8)/F6 -> 0.11647783 | G9: =(G7+G8)/G6 -> 0.13756068 | H9: =(H7+H8)/H6 -> 0.13533827 | I9: =(I7+I8)/I6 -> 0.14838272 | ... M9: =(M7+M8)/M6 -> 0.17179795
A10: Percentage of all D1+ Connected to Wi-Fi | B10: =B6/B5 -> 0.52152591 | C10: =C6/C5 -> 0.52346365 | D10: =D6/D5 -> 0.53343705 | E10: =E6/E5 -> 0.54086035 | F10: =F6/F5 -> 0.55969921 | G10: =G6/G5 -> 0.54947586 | H10: =H6/H5 -> 0.55138873 | I10: =I6/I5 -> 0.55334029 | ... M10: =M6/M5 -> 0.52010938
A11: Active Cloud Services Plans (EOM) | B11: 403 | C11: =B11+62 -> 465 | D11: =C11+106 -> 571 | E11: =D11+91 -> 662 | F11: =E11+130 -> 792 | G11: =F11+70 -> 862 | H11: =G11+59 -> 921 | I11: =H11+110 -> 1031 | J11: =I11+147 -> 1178 | K11: =J11+204 -> 1382 | L11: =K11+239 -> 1621 | M11: =L11+320 -> 1941
A12: Daikin One Cloud Services COGS | B12: =B9*B11 -> 59.389676 | C12: =C9*C11 -> 58.447419 | D12: =D9*D11 -> 64.104832 | E12: =E9*E11 -> 73.596771 | F12: =F9*F11 -> 92.250443 | G12: =G9*G11 -> 118.5773 | H12: =H9*H11 -> 124.64655 | I12: =I9*I11 -> 152.98259 | ... M12: =M9*M11 -> 333.45982
A14: Original Numbers | B14: 6496 | D14: 6971 | E14: 5105
A15: Delta | B15: =B4-B14 -> 5 | D15: =D4-D14 -> 12 | E15: =E4-E14 -> 6
A17: Total AWS | B17: =B7+B8 -> 8494.05 | C17: =C7+C8 -> 7745.1 | D17: =D7+D8 -> 7467.82 | E17: =E7+E8 -> 7805.26 | F17: =F7+F8 -> 8730.13 | G17: =G7+G8 -> 10729.32 | H17: =H7+H8 -> 10932.49 | I17: =I7+I8 -> 12432.84 | ... M17: =M7+M8 -> 16305

Sheet License Growth Graphed
C2: FY24 | L2: FY25
C3: Jul | D3: Aug | E3: Sep | F3: Oct | G3: Nov | H3: Dec | I3: Jan | J3: Feb | K3: Mar | L3: Apr | M3: May | N3: Jun | O3: Jul | P3: Aug | Q3: Sep | R3: Oct | S3: Nov | T3: Dec | U3: Jan | V3: Feb | W3: Mar
B4: New Cloud Services Sales & Activations (Monthly) | C4: 859 | D4: 726 | E4: 546 | F4: 702 | G4: 668 | H4: 661 | I4: 765 | J4: 699 | K4: 600 | L4: ='FY25'!B10 -> 680 | M4: ='FY25'!C10 -> 730 | N4: ='FY25'!D10 -> 827 | O4: ='FY25'!E10 -> 954 | P4: ='FY25'!F10 -> 856 | Q4: ='FY25'!G10 -> 707 | R4: ='FY25'!H10 -> 847 | S4: ='FY25'!I10 -> 873 | ... W4: ='FY25'!M10 -> 921
B5: Active Cloud Services Plans (EOM) | C5: 8628 | D5: 8879 | E5: 9434 | F5: 9690 | G5: 10236 | H5: 10826 | I5: 9612 | J5: 9874 | K5: 10062 | L5: ='FY25'!B11 -> 10265 | M5: ='FY25'!C11 -> 10400 | N5: ='FY25'!D11 -> 10584 | O5: ='FY25'!E11 -> 10720 | P5: ='FY25'!F11 -> 10917 | Q5: ='FY25'!G11 -> 11076 | R5: ='FY25'!H11 -> 11280 | S5: ='FY25'!I11 -> 11521 | ... W5: ='FY25'!M11 -> 12459
B6: License Growth | D6: =D5-C5 -> 251 | E6: =E5-D5 -> 555 | F6: =F5-E5 -> 256 | G6: =G5-F5 -> 546 | H6: =H5-G5 -> 590 | I6: =I5-H5 -> -1214 | J6: =J5-I5 -> 262 | K6: =K5-J5 -> 188 | ... W6: =W5-V5 -> 294
B7: ExpiredLicenses (Inferred) | D7: =D4-D6 -> 475 | E7: =E4-E6 -> -9 | F7: =F4-F6 -> 446 | G7: =G4-G6 -> 122 | H7: =H4-H6 -> 71 | I7: =I4-I6 -> 1979 | J7: =J4-J6 -> 437 | K7: =K4-K6 -> 412 | ... W7: =W4-W6 -> 627

Sheet AWS Cost Graphed
B1: FY22 | N1: FY23 | Z1: FY24 | AL1: FY25
B2: APR | C2: MAY | D2: JUN | E2: JUL | F2: AUG | G2: SEP | H2: OCT | I2: NOV | J2: DEC | K2: JAN | L2: FEB | M2: MAR | N2: APR | O2: MAY | P2: JUN | Q2: JUL | R2: AUG | S2: SEP | T2: OCT | U2: NOV | V2: DEC | W2: JAN | X2: FEB | Y2: MAR | Z2: APR | AA2: MAY | AB2: JUN | AC2: JUL | AD2: AUG | AE2: SEP | AF2: OCT | AG2: NOV | AH2: DEC | AI2: JAN | AJ2: FEB | AK2: MAR | AL2: APR | AM2: MAY | AN2: JUN | AO2: JUL | AP2: AUG | AQ2: SEP | AR2: OCT | AS2: NOV | AT2: DEC | AU2: JAN | AV2: FEB | AW2: MAR
A3: Connected Devices | B3: 57638 | C3: 61619 | D3: 66518 | E3: 70208 | F3: 74951 | G3: 77997 | H3: 80779 | I3: 83789 | J3: 86251 | K3: 88317 | L3: 90841 | M3: 94908 | N3: 99826 | O3: 105125 | P3: 114981 | Q3: 121036 | R3: 127251 | S3: 132549 | T3: 131437 | U3: 135558 | V3: 139286 | W3: 142533 | X3: 146026 | Y3: 149689 | Z3: ='FY24'!B6 -> 156063 | AA3: ='FY24'!C6 -> 166317 | AB3: ='FY24'!D6 -> 172806 | AC3: ='FY24'!E6 -> 184126 | AD3: ='FY24'!F6 -> 193334 | AE3: ='FY24'!G6 -> 201802 | AF3: ='FY24'!H6 -> 205000 | AG3: ='FY24'!I6 -> 207754 | ... AK3: ='FY24'!M6 -> 246796 | AL3: ='FY25'!B6 -> 269593 | AM3: ='FY25'!C6 -> 294481 | AN3: ='FY25'!D6 -> 299991 | AO3: ='FY25'!E6 -> 304528 | AP3: ='FY25'!F6 -> 294532 | AQ3: ='FY25'!G6 -> 302743 | AR3: ='FY25'!H6 -> 311895 | AS3: ='FY25'!I6 -> 318949 | ... AW3: ='FY25'!M6 -> 349395
A4: AWS Cost | B4: 8494.05 | C4: 7745.1 | D4: 7467.82 | E4: 7805.26 | F4: 8730.13 | G4: 10729.32 | H4: 10932.49 | I4: 12432.84 | J4: 12324.03 | K4: 16203.34 | L4: 17354.4 | M4: 16305 | N4: 16394.16 | O4: 15891.16 | P4: 22413.49 | Q4: 19836.09 | R4: 30198.21 | S4: 34299.44 | T4: 31918.66 | U4: 33947.3 | V4: 34260.46 | W4: 29606.56 | X4: 31647.81 | Y4: 35050.03 | Z4: ='FY24'!B7 -> 47433.74 | AA4: ='FY24'!C7 -> 37064.8 | AB4: ='FY24'!D7 -> 82792.92 | AC4: ='FY24'!E7 -> 57395.01 | AD4: ='FY24'!F7 -> 50593.76 | AE4: ='FY24'!G7 -> 37218.78 | AF4: ='FY24'!H7 -> 35622.87 | AG4: ='FY24'!I7 -> 30300.5 | ... AK4: ='FY24'!M7 -> 33627.65 | AL4: ='FY25'!B7 -> 35381.18 | AM4: ='FY25'!C7 -> 39890.72 | AN4: ='FY25'!D7 -> 38431.53 | AO4: ='FY25'!E7 -> 38723.87 | AP4: ='FY25'!F7 -> 40085.3 | AQ4: ='FY25'!G7 -> 38310.35 | AR4: ='FY25'!H7 -> 36721.77 | AS4: ='FY25'!I7 -> 42241.7 | ... AW4: ='FY25'!M7 -> 45550.48

Sheet Data Explanation
B2: Cell | C2: Description | D2: Data Source | E2: Notes
B3: A4 | C3: Monthly Smart Thermostat Sales (All Stats & Brands) | D3: https://prod-useast-b.online.tableau.com/#/site/daikincomfort/views/DAIKINONETHERMOSTATSDOCSSELLIN/ThermostatSalesSummary?:iid=1 | E3: You will need to filter thermostats - IAQ and Accessories are included in the list
B4: A5 | C4: Total Daikin One Sales (All-time) | D4: Auto-calculated based on a rough estimate of sales from FY19 - FY22. Sales tracking under the former split BU's had some surprising gaps, and was not a priority for Dennis or Jacky
B5: A6 | C5: Total D/A/G Thermostats Connected to Wi-Fi | D5: Pulled from the .CSV report that is emailed monthly - See "report 07.31.25.csv" attached cell B:1654 for the value needed
B6: A7 | C6: AWS Cost | D6: From AWS Invoice - Currently being emailed to me.
B7: A8 | C7: Cost per D1+ Connection (Per month) | D7: AWS monthly spend divided by total number of Wi-Fi connected thermostats
B8: A9 | C8: Percentage of all D1+ Connected to Wi-Fi | D8: Math - connected / all-time sell-in
B9: A10 | C9: New Cloud Services Sales & Activations (Monthly) | D9: https://prod-useast-b.online.tableau.com/#/site/daikincomfort/views/ResidentialControlsSolutions/MonthlySalesMTD?:iid=1 '- This can also be found in the monthly sales report emailed by Softway, CS-Monthly-Sales-XX.XX.XX, see attached example. | E9: Not used for COGS, but you and I agreed we should track this monthly. Currently we're not using this but it's a relevant metric
B10: A11 | C10: Active Cloud Services Plans (EOM) | D10: Monthly report emailed by Softway, License_Activation_Report_Jul_2025 is attached as an example '- This should be able to be pulled from the "Licenses" report on Tableau but the data does not align and Softway is not giving a firm number. i.e. - Tableau report show 10.54K for Active License count rather than a firm number. Additionally, the emailed report for July EOM shows 10,720. - This was on my list to review with Kashif and the team. | E10: Highlights the lack of renewals, and should be a key metric for us as an organization and one that sales should be tracked to moving forward.
B11: A12 | C11: Daikin One Cloud Services COGS | D11: Math - Active licenses * Cost / connection | E11: DT and I argued about using this as COGS since it's essentially doubling the cost / connection for thermostats connected to CS, and doesn't reflect actual CS costs. The reality is this is fine for now, and getting more accurate on the cost for deliverying CS will require implementing more analytical tools on our server to track cost to serve. In the future this should be reviewed.
